dagster_factory_pipelines/__init__.py
dagster_factory_pipelines/factory/__init__.py
dagster_factory_pipelines/factory/base.py
dagster_factory_pipelines/factory/factory.py
dagster_factory_pipelines/factory/models.py
dagster_factory_pipelines/factory/registry.py
dagster_factory_pipelines/factory/triggers.py
dagster_factory_pipelines/factory/yaml_validation.py
dagster_factory_pipelines-0.1.15.dist-info/METADATA
dagster_factory_pipelines-0.1.15.dist-info/WHEEL
dagster_factory_pipelines-0.1.15.dist-info/top_level.txt
dagster_factory_pipelines-0.1.15.dist-info/RECORD
