Metadata-Version: 2.4
Name: dagster-factory-pipelines
Version: 0.1.15
Summary: Create dagster pipelines by using reuseable modules and yaml configuration
Author-email: Oleg Savik <oleg.savik@ut.ee>
License: MIT
Requires-Dist: dagster
Requires-Dist: requests
Requires-Dist: aiohttp
Requires-Dist: dagster_aws
